_dareblopy.cp36-win32.pyd
dareblopy/TFRecordsDatasetIterator.py
dareblopy/__init__.py
dareblopy/data_loader.py
dareblopy/utils.py
dareblopy-0.0.5.dist-info/LICENSE
dareblopy-0.0.5.dist-info/METADATA
dareblopy-0.0.5.dist-info/WHEEL
dareblopy-0.0.5.dist-info/top_level.txt
dareblopy-0.0.5.dist-info/RECORD
