Metadata-Version: 2.1
Name: dareblopy
Version: 0.0.5
Summary: dareblopy
Home-page: https://github.com/podgorskiy/dareblopy
Author: Stanislav Pidhorskyi
Author-email: stpidhorskyi@mix.wvu.edu
License: Apache 2.0 License
Requires-Dist: numpy
